setup.py
colormyprompt/__init__.py
colormyprompt/prompt.py
colormyprompt.egg-info/PKG-INFO
colormyprompt.egg-info/SOURCES.txt
colormyprompt.egg-info/dependency_links.txt
colormyprompt.egg-info/not-zip-safe
colormyprompt.egg-info/top_level.txt