Metadata-Version: 1.0
Name: colormyprompt
Version: 0.1
Summary: This helps you access functions that let you color your prompt messages
Home-page: https://github.com/kneerunjun/colormyprompt.git
Author: kneerunjun
Author-email: kneerunjun@gmail.com
License: MIT
Platform: UNKNOWN
